trame/__init__.py
trame/modules/__init__.py
trame/modules/vtklocal.py
trame/widgets/__init__.py
trame/widgets/vtklocal.py
trame_vtklocal/__init__.py
trame_vtklocal/module/__init__.py
trame_vtklocal/module/protocol.py
trame_vtklocal/module/wasm.py
trame_vtklocal/module/serve/js/trame_vtklocal.css
trame_vtklocal/module/serve/js/trame_vtklocal.umd.js
trame_vtklocal/widgets/__init__.py
trame_vtklocal/widgets/vtklocal.py
trame_vtklocal-0.16.4.dist-info/METADATA
trame_vtklocal-0.16.4.dist-info/WHEEL
trame_vtklocal-0.16.4.dist-info/licenses/LICENSE
trame_vtklocal-0.16.4.dist-info/RECORD
