Metadata-Version: 2.4
Name: trame-vtklocal
Version: 0.16.4
Summary: VTK Local Rendering using WASM
Author: Kitware Inc.
License: Apache Software License
License-File: LICENSE
Keywords: Application,Framework,Interactive,Python,Web
Classifier: Development Status :: 5 - Production/Stable
Classifier: Environment :: Web Environment
Classifier: License :: OSI Approved :: Apache Software License
Classifier: Natural Language :: English
Classifier: Operating System :: OS Independent
Classifier: Programming Language :: Python :: 3 :: Only
Classifier: Topic :: Software Development :: Libraries :: Application Frameworks
Classifier: Topic :: Software Development :: Libraries :: Python Modules
Requires-Python: >=3.9
Requires-Dist: packaging
Requires-Dist: trame
Requires-Dist: trame-common
Provides-Extra: dev
Requires-Dist: pre-commit; extra == 'dev'
Requires-Dist: pytest; extra == 'dev'
Requires-Dist: pytest-asyncio; extra == 'dev'
Requires-Dist: ruff; extra == 'dev'
Requires-Dist: trame-client[test]; extra == 'dev'
Provides-Extra: vtk
Requires-Dist: vtk>=9.4; extra == 'vtk'
